tarski_lapkt/__init__.py
tarski_lapkt/errors.py
tarski_lapkt/fol.py
tarski_lapkt/model.py
tarski_lapkt/modules.py
tarski_lapkt/theories.py
tarski_lapkt/util.py
tarski_lapkt/version.py
tarski_lapkt/analysis/__init__.py
tarski_lapkt/analysis/csp.py
tarski_lapkt/analysis/csp_schema.py
tarski_lapkt/benchmarks/__init__.py
tarski_lapkt/benchmarks/blocksworld.py
tarski_lapkt/benchmarks/counters.py
tarski_lapkt/dl/__init__.py
tarski_lapkt/dl/concepts.py
tarski_lapkt/dl/errors.py
tarski_lapkt/dl/factory.py
tarski_lapkt/dl/features.py
tarski_lapkt/evaluators/__init__.py
tarski_lapkt/evaluators/simple.py
tarski_lapkt/fstrips/__init__.py
tarski_lapkt/fstrips/action.py
tarski_lapkt/fstrips/derived.py
tarski_lapkt/fstrips/errors.py
tarski_lapkt/fstrips/fstrips.py
tarski_lapkt/fstrips/ops.py
tarski_lapkt/fstrips/problem.py
tarski_lapkt/fstrips/representation.py
tarski_lapkt/fstrips/visitors.py
tarski_lapkt/fstrips/walker.py
tarski_lapkt/fstrips/contingent/__init__.py
tarski_lapkt/fstrips/contingent/errors.py
tarski_lapkt/fstrips/contingent/problem.py
tarski_lapkt/fstrips/contingent/sensor.py
tarski_lapkt/fstrips/hybrid/__init__.py
tarski_lapkt/fstrips/hybrid/differential_constraints.py
tarski_lapkt/fstrips/hybrid/errors.py
tarski_lapkt/fstrips/hybrid/problem.py
tarski_lapkt/fstrips/hybrid/reaction.py
tarski_lapkt/fstrips/manipulation/__init__.py
tarski_lapkt/fstrips/manipulation/simplify.py
tarski_lapkt/fstrips/manipulation/types.py
tarski_lapkt/funcsym/__init__.py
tarski_lapkt/grounding/__init__.py
tarski_lapkt/grounding/common.py
tarski_lapkt/grounding/errors.py
tarski_lapkt/grounding/lp_grounding.py
tarski_lapkt/grounding/naive_grounding.py
tarski_lapkt/grounding/ops.py
tarski_lapkt/grounding/naive/__init__.py
tarski_lapkt/grounding/naive/constraints.py
tarski_lapkt/grounding/naive/diff_constraints.py
tarski_lapkt/grounding/naive/instantiation.py
tarski_lapkt/grounding/naive/reactions.py
tarski_lapkt/grounding/naive/sensors.py
tarski_lapkt/grounding/naive/state_variables.py
tarski_lapkt-0.1.3.dist-info/LICENSE
tarski_lapkt-0.1.3.dist-info/METADATA
tarski_lapkt-0.1.3.dist-info/WHEEL
tarski_lapkt-0.1.3.dist-info/top_level.txt
tarski_lapkt-0.1.3.dist-info/RECORD
